blidec_paste-3.2.4-py3.7-nspkg.pth
paste/cascade.py
paste/cgiapp.py
paste/cgitb_catcher.py
paste/config.py
paste/errordocument.py
paste/fileapp.py
paste/fixture.py
paste/flup_session.py
paste/gzipper.py
paste/httpexceptions.py
paste/httpheaders.py
paste/httpserver.py
paste/lint.py
paste/modpython.py
paste/pony.py
paste/progress.py
paste/proxy.py
paste/recursive.py
paste/registry.py
paste/reloader.py
paste/request.py
paste/response.py
paste/session.py
paste/transaction.py
paste/translogger.py
paste/url.py
paste/urlmap.py
paste/urlparser.py
paste/wsgilib.py
paste/wsgiwrappers.py
paste/auth/__init__.py
paste/auth/auth_tkt.py
paste/auth/basic.py
paste/auth/cas.py
paste/auth/cookie.py
paste/auth/digest.py
paste/auth/form.py
paste/auth/grantip.py
paste/auth/multi.py
paste/auth/open_id.py
paste/cowbell/__init__.py
paste/cowbell/bell-ascending.png
paste/cowbell/bell-descending.png
paste/debug/__init__.py
paste/debug/debugapp.py
paste/debug/doctest_webapp.py
paste/debug/fsdiff.py
paste/debug/prints.py
paste/debug/profile.py
paste/debug/testserver.py
paste/debug/watchthreads.py
paste/debug/wdg_validate.py
paste/evalexception/__init__.py
paste/evalexception/evalcontext.py
paste/evalexception/middleware.py
paste/evalexception/media/MochiKit.packed.js
paste/evalexception/media/debug.js
paste/evalexception/media/minus.jpg
paste/evalexception/media/plus.jpg
paste/exceptions/__init__.py
paste/exceptions/collector.py
paste/exceptions/errormiddleware.py
paste/exceptions/formatter.py
paste/exceptions/reporter.py
paste/exceptions/serial_number_generator.py
paste/util/PySourceColor.py
paste/util/__init__.py
paste/util/classinit.py
paste/util/classinstance.py
paste/util/converters.py
paste/util/dateinterval.py
paste/util/datetimeutil.py
paste/util/filemixin.py
paste/util/finddata.py
paste/util/findpackage.py
paste/util/html.py
paste/util/import_string.py
paste/util/intset.py
paste/util/ip4.py
paste/util/killthread.py
paste/util/looper.py
paste/util/mimeparse.py
paste/util/multidict.py
blidec_paste-3.2.4.dist-info/METADATA
blidec_paste-3.2.4.dist-info/WHEEL
blidec_paste-3.2.4.dist-info/entry_points.txt
blidec_paste-3.2.4.dist-info/namespace_packages.txt
blidec_paste-3.2.4.dist-info/top_level.txt
blidec_paste-3.2.4.dist-info/RECORD
