Metadata-Version: 2.1
Name: blidec-paste
Version: 3.2.4
Summary: Tools for using a Web Server Gateway Interface stack
Home-page: https://pythonpaste.readthedocs.io/
Author: Benhong Li
Author-email: benhongli.ca@gmail.com
License: MIT
Keywords: web application server wsgi
Platform: UNKNOWN
Classifier: Development Status :: 5 - Production/Stable
Classifier: Intended Audience :: Developers
Classifier: License :: OSI Approved :: MIT License
Classifier: Programming Language :: Python
Classifier: Programming Language :: Python :: 3
Classifier: Topic :: Internet :: WWW/HTTP
Classifier: Topic :: Internet :: WWW/HTTP :: Dynamic Content
Classifier: Topic :: Software Development :: Libraries :: Python Modules
Classifier: Topic :: Internet :: WWW/HTTP :: WSGI
Classifier: Topic :: Internet :: WWW/HTTP :: WSGI :: Application
Classifier: Topic :: Internet :: WWW/HTTP :: WSGI :: Middleware
Classifier: Topic :: Internet :: WWW/HTTP :: WSGI :: Server
Classifier: Framework :: Paste
Requires-Dist: six (>=1.4.0)
Provides-Extra: flup
Requires-Dist: flup ; extra == 'flup'
Provides-Extra: paste
Provides-Extra: hotshot
Provides-Extra: openid
Requires-Dist: python-openid ; extra == 'openid'
Provides-Extra: subprocess
